torchmaxflowcpp.cp37-win_amd64.pyd
torchmaxflow/__init__.py
torchmaxflow-0.0.7.dist-info/LICENSE
torchmaxflow-0.0.7.dist-info/METADATA
torchmaxflow-0.0.7.dist-info/WHEEL
torchmaxflow-0.0.7.dist-info/top_level.txt
torchmaxflow-0.0.7.dist-info/RECORD
