Metadata-Version: 2.1
Name: torchmaxflow
Version: 0.0.7
Summary: torchmaxflow: Max-flow/Min-cut in PyTorch for 2D images and 3D volumes
Home-page: https://github.com/masadcv/torchmaxflow
Author: Muhammad Asad
Author-email: masadcv@gmail.com
License: BSD-3-Clause License
Platform: UNKNOWN
Classifier: License :: OSI Approved :: BSD License
Classifier: Programming Language :: Python :: 3
Requires-Dist: torch (>=1.10.0)
